name_a_toon/__init__.py
name_a_toon/gen.py
name_a_toon/regex.py
name_a_toon-0.0.1.dist-info/LICENSE
name_a_toon-0.0.1.dist-info/METADATA
name_a_toon-0.0.1.dist-info/WHEEL
name_a_toon-0.0.1.dist-info/top_level.txt
name_a_toon-0.0.1.dist-info/RECORD
