Metadata-Version: 2.1
Name: name_a_toon
Version: 0.0.1
Summary: A Python package to make naming Toons easier!
Author-email: Vhou-Atroph <vhouatroph@proton.me>
Project-URL: Homepage, https://github.com/Vhou-Atroph/name-a-toon
Project-URL: Bug Tracker, https://github.com/Vhou-Atroph/name-a-toon/issues
Classifier: Programming Language :: Python :: 3
Classifier: License :: OSI Approved :: MIT License
Classifier: Operating System :: OS Independent
Requires-Python: >=3.11
License-File: LICENSE
